minikerberos/__init__.py
minikerberos/_version.py
minikerberos/aioclient.py
minikerberos/client.py
minikerberos/pkinit.py
minikerberos/security.py
minikerberos/common/__init__.py
minikerberos/common/ccache.py
minikerberos/common/constants.py
minikerberos/common/creds.py
minikerberos/common/factory.py
minikerberos/common/keytab.py
minikerberos/common/kirbi.py
minikerberos/common/spn.py
minikerberos/common/target.py
minikerberos/common/utils.py
minikerberos/common/windows/__init__.py
minikerberos/common/windows/crypt32.py
minikerberos/common/windows/defines.py
minikerberos/examples/CVE_2022_33647.py
minikerberos/examples/CVE_2022_33679.py
minikerberos/examples/__init__.py
minikerberos/examples/__main__.py
minikerberos/examples/asreproast.py
minikerberos/examples/ccache2kirbi.py
minikerberos/examples/ccache_editor.py
minikerberos/examples/ccacheroast.py
minikerberos/examples/changepassword.py
minikerberos/examples/crosstest.py
minikerberos/examples/getNT.py
minikerberos/examples/getS4U2proxy.py
minikerberos/examples/getS4U2self.py
minikerberos/examples/getTGS.py
minikerberos/examples/getTGT.py
minikerberos/examples/kerb23hashdecrypt.py
minikerberos/examples/kirbi2ccache.py
minikerberos/examples/spnroast.py
minikerberos/gssapi/__init__.py
minikerberos/gssapi/channelbindings.py
minikerberos/gssapi/gssapi.py
minikerberos/network/__init__.py
minikerberos/network/aioclientsocket.py
minikerberos/network/clientsocket.py
minikerberos/protocol/__init__.py
minikerberos/protocol/asn1_structs.py
minikerberos/protocol/constants.py
minikerberos/protocol/dirtydh.py
minikerberos/protocol/encryption.py
minikerberos/protocol/errors.py
minikerberos/protocol/mskile.py
minikerberos/protocol/rfc3244.py
minikerberos/protocol/rfc4556.py
minikerberos/protocol/rfc_iakerb.py
minikerberos/protocol/structures.py
minikerberos/protocol/ticketutils.py
minikerberos/protocol/external/__init__.py
minikerberos/protocol/external/dtypes.py
minikerberos/protocol/external/enum.py
minikerberos_bad-0.4.15.dist-info/licenses/LICENSE
minikerberos_bad-0.4.15.dist-info/METADATA
minikerberos_bad-0.4.15.dist-info/WHEEL
minikerberos_bad-0.4.15.dist-info/entry_points.txt
minikerberos_bad-0.4.15.dist-info/top_level.txt
minikerberos_bad-0.4.15.dist-info/zip-safe
minikerberos_bad-0.4.15.dist-info/RECORD
